send_steps.py
send_steps-0.1.0.dist-info/METADATA
send_steps-0.1.0.dist-info/WHEEL
send_steps-0.1.0.dist-info/entry_points.txt
send_steps-0.1.0.dist-info/top_level.txt
send_steps-0.1.0.dist-info/RECORD
