Metadata-Version: 2.1
Name: send-steps
Version: 0.1.0
Requires-Dist: click
Requires-Dist: requests
Requires-Dist: python-dotenv
Requires-Dist: python-gitlab
Requires-Dist: radish-bdd
